eeg_to_fmri/__init__.py
eeg_to_fmri/data/__init__.py
eeg_to_fmri/data/data_utils.py
eeg_to_fmri/data/eeg_utils.py
eeg_to_fmri/data/fmri_utils.py
eeg_to_fmri/data/outlier_utils.py
eeg_to_fmri/data/preprocess_data.py
eeg_to_fmri/explainability/__init__.py
eeg_to_fmri/explainability/lrp.py
eeg_to_fmri/layers/__init__.py
eeg_to_fmri/layers/bayesian.py
eeg_to_fmri/layers/fft.py
eeg_to_fmri/layers/fourier_features.py
eeg_to_fmri/layers/latent_attention.py
eeg_to_fmri/layers/mask.py
eeg_to_fmri/layers/resnet_block.py
eeg_to_fmri/layers/style.py
eeg_to_fmri/layers/topographical_attention.py
eeg_to_fmri/learning/__init__.py
eeg_to_fmri/learning/losses.py
eeg_to_fmri/learning/train.py
eeg_to_fmri/metrics/__init__.py
eeg_to_fmri/metrics/bnn.py
eeg_to_fmri/metrics/quantitative_metrics.py
eeg_to_fmri/models/__init__.py
eeg_to_fmri/models/classifiers.py
eeg_to_fmri/models/fmri_ae.py
eeg_to_fmri/models/synthesizers.py
eeg_to_fmri/regularizers/__init__.py
eeg_to_fmri/regularizers/activity_regularizers.py
eeg_to_fmri/regularizers/path_sgd.py
eeg_to_fmri/utils/__init__.py
eeg_to_fmri/utils/print_utils.py
eeg_to_fmri/utils/tf_config.py
eeg_to_fmri/utils/viz_utils.py
eeg_to_fmri-0.0.9.dist-info/LICENSE
eeg_to_fmri-0.0.9.dist-info/METADATA
eeg_to_fmri-0.0.9.dist-info/WHEEL
eeg_to_fmri-0.0.9.dist-info/top_level.txt
eeg_to_fmri-0.0.9.dist-info/RECORD
