Metadata-Version: 2.1
Name: eeg-to-fmri
Version: 0.0.9
Author-email: David Calhas <eeg_to_fmri@outlook.com>
License: MIT License
Project-URL: home, https://dcalhas.github.io/eeg_to_fmri/
Project-URL: repository, https://github.com/eeg-to-fmri/eeg-to-fmri
Keywords: eeg,fmri,synthesis,deep learning,learning,machine learning,computer vision
Classifier: License :: OSI Approved :: MIT License
Classifier: Programming Language :: Python
Classifier: Programming Language :: Python :: 3
Requires-Python: >=3.8
License-File: LICENSE
Requires-Dist: tensorflow (==2.9.0)
Requires-Dist: matplotlib (==3.5.3)
Requires-Dist: mne (==0.23.4)
Requires-Dist: nilearn (==0.7.0)
Requires-Dist: tensorflow-probability (==0.12.2)
Requires-Dist: tensorflow-determinism (==0.3.0)
Requires-Dist: tensorflow-addons (==0.19.0)
